aliyunsdkdyvmsapi/__init__.py
aliyunsdkdyvmsapi/endpoint.py
aliyunsdkdyvmsapi/request/__init__.py
aliyunsdkdyvmsapi/request/v20170525/AddRtcAccountRequest.py
aliyunsdkdyvmsapi/request/v20170525/AddVirtualNumberRelationRequest.py
aliyunsdkdyvmsapi/request/v20170525/BatchRobotSmartCallRequest.py
aliyunsdkdyvmsapi/request/v20170525/BindNumberAndVoipIdRequest.py
aliyunsdkdyvmsapi/request/v20170525/CancelCallRequest.py
aliyunsdkdyvmsapi/request/v20170525/CancelOrderRobotTaskRequest.py
aliyunsdkdyvmsapi/request/v20170525/CancelRobotTaskRequest.py
aliyunsdkdyvmsapi/request/v20170525/ClickToDialRequest.py
aliyunsdkdyvmsapi/request/v20170525/CloseSipAccountRequest.py
aliyunsdkdyvmsapi/request/v20170525/CreateCallTaskRequest.py
aliyunsdkdyvmsapi/request/v20170525/CreateRobotTaskRequest.py
aliyunsdkdyvmsapi/request/v20170525/CreateSipAccountRequest.py
aliyunsdkdyvmsapi/request/v20170525/DeleteRobotTaskRequest.py
aliyunsdkdyvmsapi/request/v20170525/DescribeRecordDataRequest.py
aliyunsdkdyvmsapi/request/v20170525/DoRtcNumberAuthRequest.py
aliyunsdkdyvmsapi/request/v20170525/DoubleCallSeatRequest.py
aliyunsdkdyvmsapi/request/v20170525/ExecuteCallTaskRequest.py
aliyunsdkdyvmsapi/request/v20170525/GetCallInfoRequest.py
aliyunsdkdyvmsapi/request/v20170525/GetHotlineQualificationByOrderRequest.py
aliyunsdkdyvmsapi/request/v20170525/GetRtcTokenRequest.py
aliyunsdkdyvmsapi/request/v20170525/GetTokenRequest.py
aliyunsdkdyvmsapi/request/v20170525/IvrCallRequest.py
aliyunsdkdyvmsapi/request/v20170525/ListCallTaskDetailRequest.py
aliyunsdkdyvmsapi/request/v20170525/ListCallTaskRequest.py
aliyunsdkdyvmsapi/request/v20170525/ListHotlineTransferNumberRequest.py
aliyunsdkdyvmsapi/request/v20170525/ListHotlineTransferRegisterFileRequest.py
aliyunsdkdyvmsapi/request/v20170525/ListOrderedNumbersRequest.py
aliyunsdkdyvmsapi/request/v20170525/ListOutboundStrategiesRequest.py
aliyunsdkdyvmsapi/request/v20170525/ListRobotTaskCallsRequest.py
aliyun_python_sdk_dyvmsapi-3.2.0.dist-info/LICENSE
aliyun_python_sdk_dyvmsapi-3.2.0.dist-info/METADATA
aliyun_python_sdk_dyvmsapi-3.2.0.dist-info/WHEEL
aliyun_python_sdk_dyvmsapi-3.2.0.dist-info/top_level.txt
aliyun_python_sdk_dyvmsapi-3.2.0.dist-info/RECORD
